{"stats":{"minecraft:used":{"minecraft:smithing_table":1,"minecraft:stone":12,"les_thons_rouges:uraniumpickaxe":15},"minecraft:custom":{"minecraft:time_since_rest":4402,"minecraft:interact_with_smithing_table":1,"minecraft:walk_one_cm":4892,"minecraft:play_time":10839,"minecraft:sprint_one_cm":3574,"minecraft:damage_taken":380,"minecraft:deaths":1,"minecraft:sneak_time":373,"minecraft:jump":56,"minecraft:leave_game":1,"minecraft:time_since_death":4336,"minecraft:total_world_time":13240,"minecraft:fall_one_cm":6718,"minecraft:fly_one_cm":30135},"minecraft:mined":{"les_thons_rouges:uraniumblock":2,"minecraft:dirt":3,"minecraft:deepslate_diamond_ore":2,"minecraft:stone":3,"minecraft:deepslate":4,"minecraft:deepslate_lapis_ore":1},"minecraft:crafted":{"minecraft:air":0},"minecraft:picked_up":{"les_thons_rouges:uraniumarmure_helmet":1,"minecraft:stone":58,"minecraft:diamond":2,"minecraft:cobbled_deepslate":35,"les_thons_rouges:uraniumarmure_leggings":1,"minecraft:tuff":8,"les_thons_rouges:rafura":4,"les_thons_rouges:uraniumpickaxe":1,"les_thons_rouges:uraniumarmure_chestplate":1,"les_thons_rouges:uraniumarmure_boots":1,"minecraft:lapis_lazuli":6,"minecraft:dirt":2,"minecraft:cobblestone":16}},"DataVersion":3120}